{
  "_comment": "3 days of normal baseline readings before the outbreak begins - needed to establish rolling averages",
  "readings": [
    {
      "_day": "Baseline Day 1",
      "timestamp": "2026-04-20T08:00:00+08:00",
      "temperature_celsius": 30.1,
      "feed_intake_kg": 50.5,
      "mortality_count": 1,
      "farmer_notes": "Semua nampak sihat"
    },
    {
      "_day": "Baseline Day 2",
      "timestamp": "2026-04-21T08:00:00+08:00",
      "temperature_celsius": 29.9,
      "feed_intake_kg": 49.5,
      "mortality_count": 1,
      "farmer_notes": "Normal"
    },
    {
      "_day": "Baseline Day 3",
      "timestamp": "2026-04-22T08:00:00+08:00",
      "temperature_celsius": 30.0,
      "feed_intake_kg": 50.0,
      "mortality_count": 1,
      "farmer_notes": "Normal"
    }
  ]
}
